ntfy_handler/__init__.py
ntfy_handler/ntfy_handler.py
ntfy_handler-1.0.4.dist-info/LICENSE
ntfy_handler-1.0.4.dist-info/METADATA
ntfy_handler-1.0.4.dist-info/WHEEL
ntfy_handler-1.0.4.dist-info/top_level.txt
ntfy_handler-1.0.4.dist-info/RECORD
