Metadata-Version: 2.1
Name: ntfy_handler
Version: 1.0.4
Summary: An extremely simple logging handler for relaying log events to ntfy
Author-email: Scott Conway <pypi@conway.scot>
License: MIT License
Project-URL: Home, https://github.com/scottmconway/ntfy-handler
Classifier: License :: OSI Approved :: MIT License
Classifier: Operating System :: OS Independent
Classifier: Programming Language :: Python :: 3 :: Only
License-File: LICENSE
Requires-Dist: requests >=2.6
